leakix/__init__.py
leakix/client.py
leakix/domain.py
leakix/field.py
leakix/plugin.py
leakix/query.py
leakix/response.py
leakix-0.1.10.dist-info/LICENSE
leakix-0.1.10.dist-info/METADATA
leakix-0.1.10.dist-info/WHEEL
leakix-0.1.10.dist-info/RECORD
