Metadata-Version: 2.1
Name: leakix
Version: 0.1.10
Summary: Official python client for LeakIX (https://leakix.net)
Author: Danny Willems
Author-email: danny@leakix.net
Requires-Python: >=3.7,<4.0
Classifier: Programming Language :: Python :: 3
Classifier: Programming Language :: Python :: 3.7
Classifier: Programming Language :: Python :: 3.8
Classifier: Programming Language :: Python :: 3.9
Classifier: Programming Language :: Python :: 3.10
Classifier: Programming Language :: Python :: 3.11
Requires-Dist: fire (>=0.5.0,<0.6.0)
Requires-Dist: l9format (==1.3.1a3)
Requires-Dist: requests
